{
	"skills": [ 
		{
			"skill": "Algorithms",
			"tasks": [
				{
					"task": 1,
					"description": "Create a snippet that completes task 1"
				},
				{
					"task": 2,
					"description": "Create a snippet that completes task 2"
				},				
				{
					"task": 3,
					"description": "Create a snippet that completes task 3"
				},
				{
					"task": 4,
					"description": "Create a snippet that completes task 4"
				},
				{
					"task": 5,
					"description": "Create a snippet that completes task 5"
				},
				{
					"task": 6,
					"description": "Create a snippet that completes task 6"
				},
				{
					"task": 7,
					"description": "Create a snippet that completes task 7"
				},
				{
					"task": 8,
					"description": "Create a snippet that completes task 8"
				},
				{
					"task": 9,
					"description": "Create a snippet that completes task 9"
				},
				{
					"task": 10,
					"description": "Create a snippet that completes task 10"
				},
				{
					"task": 11,
					"description": "Create a snippet that completes task 11"
				},
				{
					"task": 12,
					"description": "Create a snippet that completes task 12"
				},
				{
					"task": 13,
					"description": "Create a snippet that completes task 13"
				},
				{
					"task": 14,
					"description": "Create a snippet that completes task 14"
				},
				{
					"task": 15,
					"description": "Create a snippet that completes task 15"
				},
				{
					"task": 16,
					"description": "Create a snippet that completes task 16"
				},
				{
					"task": 17,
					"description": "Create a snippet that completes task 17"
				},
				{
					"task": 18,
					"description": "Create a snippet that completes task 18"
				},
				{
					"task": 19,
					"description": "Create a snippet that completes task 19"
				},
				{
					"task": 20,
					"description": "Create a snippet that completes task 20"
				},
				{
					"task": 21,
					"description": "Create a snippet that completes task 21"
				},
				{
					"task": 22,
					"description": "Create a snippet that completes task 22"
				},
				{
					"task": 23,
					"description": "Create a snippet that completes task 23"
				},
				{
					"task": 24,
					"description": "Create a snippet that completes task 24"
				},
				{
					"task": 25,
					"description": "Create a snippet that completes task 25"
				},
				{
					"task": 26,
					"description": "Create a snippet that completes task 26"
				},
				{
					"task": 27,
					"description": "Create a snippet that completes task 27"
				},
				{
					"task": 28,
					"description": "Create a snippet that completes task 28"
				},
				{
					"task": 29,
					"description": "Create a snippet that completes task 29"
				},
				{
					"task": 30,
					"description": "Create a snippet that completes task 30"
				}
			]
		},
		{
			"skill": "Data structures",
			"tasks": [
				{
					"task": 1,
					"description": "Create a snippet that completes task 1"
				},
				{
					"task": 2,
					"description": "Create a snippet that completes task 2"
				},				
				{
					"task": 3,
					"description": "Create a snippet that completes task 3"
				},
				{
					"task": 4,
					"description": "Create a snippet that completes task 4"
				},
				{
					"task": 5,
					"description": "Create a snippet that completes task 5"
				},
				{
					"task": 6,
					"description": "Create a snippet that completes task 6"
				},
				{
					"task": 7,
					"description": "Create a snippet that completes task 7"
				},
				{
					"task": 8,
					"description": "Create a snippet that completes task 8"
				},
				{
					"task": 9,
					"description": "Create a snippet that completes task 9"
				},
				{
					"task": 10,
					"description": "Create a snippet that completes task 10"
				},
				{
					"task": 11,
					"description": "Create a snippet that completes task 11"
				},
				{
					"task": 12,
					"description": "Create a snippet that completes task 12"
				},
				{
					"task": 13,
					"description": "Create a snippet that completes task 13"
				},
				{
					"task": 14,
					"description": "Create a snippet that completes task 14"
				},
				{
					"task": 15,
					"description": "Create a snippet that completes task 15"
				},
				{
					"task": 16,
					"description": "Create a snippet that completes task 16"
				},
				{
					"task": 17,
					"description": "Create a snippet that completes task 17"
				},
				{
					"task": 18,
					"description": "Create a snippet that completes task 18"
				},
				{
					"task": 19,
					"description": "Create a snippet that completes task 19"
				},
				{
					"task": 20,
					"description": "Create a snippet that completes task 20"
				},
				{
					"task": 21,
					"description": "Create a snippet that completes task 21"
				},
				{
					"task": 22,
					"description": "Create a snippet that completes task 22"
				},
				{
					"task": 23,
					"description": "Create a snippet that completes task 23"
				},
				{
					"task": 24,
					"description": "Create a snippet that completes task 24"
				},
				{
					"task": 25,
					"description": "Create a snippet that completes task 25"
				},
				{
					"task": 26,
					"description": "Create a snippet that completes task 26"
				},
				{
					"task": 27,
					"description": "Create a snippet that completes task 27"
				},
				{
					"task": 28,
					"description": "Create a snippet that completes task 28"
				},
				{
					"task": 29,
					"description": "Create a snippet that completes task 29"
				},
				{
					"task": 30,
					"description": "Create a snippet that completes task 30"
				}
			]
		}
	]
}